sparc/__init__.py
sparc/ion.py
sparc/mongo.py
sparc/sparc_core.py
sparc/utilities.py
sparc_dft_api-0.1.dist-info/LICENSE
sparc_dft_api-0.1.dist-info/METADATA
sparc_dft_api-0.1.dist-info/WHEEL
sparc_dft_api-0.1.dist-info/top_level.txt
sparc_dft_api-0.1.dist-info/RECORD
